uniauth/__init__.py
uniauth/base.py
uniauth/consumers.py
uniauth/oauth1.py
uniauth/oauth2.py
uniauth-0.0.2.dist-info/DESCRIPTION.rst
uniauth-0.0.2.dist-info/METADATA
uniauth-0.0.2.dist-info/metadata.json
uniauth-0.0.2.dist-info/RECORD
uniauth-0.0.2.dist-info/top_level.txt
uniauth-0.0.2.dist-info/WHEEL
