Metadata-Version: 2.0
Name: uniauth
Version: 0.0.2
Summary: Minimalist and framework independent OAuth(1 & 2) consumers
Home-page: https://github.com/OohlaLabs/uniauth
Author: Thierry Jossermoz
Author-email: thierry.jossermoz@oohlalabs.com
License: MIT
Platform: UNKNOWN
Classifier: Development Status :: 3 - Alpha
Classifier: Environment :: Web Environment
Classifier: Intended Audience :: Developers
Classifier: Operating System :: OS Independent
Classifier: Programming Language :: Python
Classifier: Programming Language :: Python :: 2.7
Classifier: Programming Language :: Python :: 3.3
Classifier: Programming Language :: Python :: 3.4
Requires-Dist: oauthlib (>=0.7.2)
Requires-Dist: requests (>=2.5.1)
Requires-Dist: pytz (>=2014.10)
Requires-Dist: six (>=1.9.0)
Requires-Dist: python-dateutil (>=2.4.2)
